pvn/__init__.py
pvn/core/__init__.py
pvn/core/objeto.py
pvn/core/terminal.py
pvn/transporte/__init__.py
pvn/transporte/extracao.py
pvn-0.0.8.dist-info/LICENCE
pvn-0.0.8.dist-info/METADATA
pvn-0.0.8.dist-info/WHEEL
pvn-0.0.8.dist-info/top_level.txt
pvn-0.0.8.dist-info/RECORD
